{
  "$schema": "https://mintlify.com/docs.json",
  "name": "Mapas Culturais",
  "theme": "almond",
  "colors": {
    "primary": "#2d7a4f",
    "light": "#e8f5ee",
    "dark": "#1a4d31"
  },
  "navbar": {
    "primary": {
      "type": "github",
      "href": "https://github.com/redemapas/mapas"
    }
  },
  "footer": {
    "socials": {
      "github": "https://github.com/redemapas/mapas"
    }
  },
  "navigation": {
    "tabs": [
      {
        "tab": "Documentação",
        "groups": [
          {
            "group": "Introdução",
            "pages": [
              "introduction",
              "quickstart"
            ]
          },
          {
            "group": "Funcionalidades",
            "pages": [
              "features/agents",
              "features/spaces",
              "features/events",
              "features/projects",
              "features/opportunities",
              "features/registrations"
            ]
          },
          {
            "group": "Instalação e Deploy",
            "pages": [
              "deploy/docker",
              "deploy/kubernetes",
              "deploy/configuration"
            ]
          },
          {
            "group": "Desenvolvimento",
            "pages": [
              "development/architecture",
              "development/themes",
              "development/modules",
              "development/hooks",
              "development/testing"
            ]
          },
          {
            "group": "Autenticação e Permissões",
            "pages": [
              "auth/providers",
              "auth/permissions"
            ]
          }
        ]
      },
      {
        "tab": "API Reference",
        "groups": [
          {
            "group": "Visão Geral",
            "pages": [
              "api/overview",
              "api/querying"
            ]
          },
          {
            "group": "Endpoints",
            "pages": [
              "api/agents",
              "api/spaces",
              "api/events",
              "api/projects",
              "api/opportunities",
              "api/registrations"
            ]
          }
        ]
      }
    ]
  }
}
